{
  "updated": "2026-07-03T19:45:33Z",
  "phase": "upcoming",
  "race": {
    "name": "British Grand Prix",
    "round": "9",
    "season": "2026",
    "date": "2026-07-05",
    "circuit": "Silverstone Circuit"
  },
  "summary": "Russell brings momentum to Silverstone after a mature victory in Austria, but faces a formidable challenge from Hamilton, who has dominated practice and claimed pole for the sprint race in his Ferrari. McLaren's consistency and Red Bull's track-specific setup decisions could prove decisive on a circuit transformed by the new generation of cars. A strong showing at his home track could shift Russell's championship trajectory against a resurgent Hamilton, with sprint race points adding crucial weight to Sunday's main event."
}