{
  "updated": "2026-07-05T19:40:15Z",
  "phase": "post-race",
  "race": {
    "name": "British Grand Prix",
    "round": "9",
    "season": "2026",
    "date": "2026-07-05",
    "circuit": "Silverstone Circuit"
  },
  "summary": "Charles Leclerc navigated an incident-packed race to finish ahead of George Russell, while both pole-sitter Kimi Antonelli and Max Verstappen crashed out of contention. Russell's second-place finish marked a strong recovery after a chaotic opening lap that shuffled the grid's hierarchy. Leclerc's victory extends his championship lead as Mercedes struggles to convert its qualifying advantage into race points."
}